{
  "frames": [
    {
      "filename": "No click",
      "frame": {
        "x": 0,
        "y": 0,
        "w": 500,
        "h": 500
      },
      "rotated": false,
      "trimmed": false,
      "spriteSourceSize": {
        "x": 0,
        "y": 0,
        "w": 500,
        "h": 500
      },
      "sourceSize": {
        "w": 500,
        "h": 500
      },
      "custom": {
        "scale": 1,
        "rotation": 0
      }
    },
    {
      "filename": "Left Click",
      "frame": {
        "x": 500,
        "y": 0,
        "w": 500,
        "h": 500
      },
      "rotated": false,
      "trimmed": false,
      "spriteSourceSize": {
        "x": 0,
        "y": 0,
        "w": 500,
        "h": 500
      },
      "sourceSize": {
        "w": 500,
        "h": 500
      },
      "custom": {
        "scale": 1,
        "rotation": 0
      }
    },
    {
      "filename": "Right Click",
      "frame": {
        "x": 1000,
        "y": 0,
        "w": 500,
        "h": 500
      },
      "rotated": false,
      "trimmed": false,
      "spriteSourceSize": {
        "x": 0,
        "y": 0,
        "w": 500,
        "h": 500
      },
      "sourceSize": {
        "w": 500,
        "h": 500
      },
      "custom": {
        "scale": 1,
        "rotation": 0
      }
    }
  ],
  "meta": {
    "app": "Spritesheet Tool Pro",
    "version": "1.0.0",
    "image": "Mouse Click.png",
    "format": "RGBA8888",
    "size": {
      "w": 1500,
      "h": 500
    },
    "scale": 1
  }
}